examples/example.py
regmap/__init__.py
regmap/_version.py
regmap/bitfield.py
regmap/interface.py
regmap/register.py
tests/__init__.py
tests/test_register.py
regmap-0.2.0.dist-info/LICENSE
regmap-0.2.0.dist-info/METADATA
regmap-0.2.0.dist-info/WHEEL
regmap-0.2.0.dist-info/top_level.txt
regmap-0.2.0.dist-info/RECORD
