Metadata-Version: 2.1
Name: regmap
Version: 0.2.0
Summary: A lightweight library to manage direct register field manipulation.
License: MIT License
Project-URL: Repository, https://github.com/8BitJosh/regmap
Requires-Python: >=3.8
License-File: LICENSE
Provides-Extra: dev
Requires-Dist: build; extra == "dev"
Requires-Dist: pytest; extra == "dev"
Requires-Dist: ruff<0.4,>=0.3.0; extra == "dev"
